Metadata-Version: 2.4
Name: neuron_v0.4.2
Version: 0.4.2
Summary: Neuron AI Assistant — auto GPU/CPU detection and local AI.
Home-page: https://github.com/yourusername/neuron-assistant
Author: Dev Patel
Author-email: devpatel2u@gmail.com
Requires-Python: >=3.10
Requires-Dist: torch
Requires-Dist: transformers
Requires-Dist: huggingface-hub
Requires-Dist: cryptography
Requires-Dist: psutilgpt4all
Dynamic: author
Dynamic: author-email
Dynamic: description
Dynamic: description-content-type
Dynamic: home-page
Dynamic: requires-dist
Dynamic: requires-python
Dynamic: summary
